Metadata-Version: 2.1
Name: odoo14-addon-account_payment_order_tier_validation
Version: 14.0.1.0.1.dev20
Summary: Extends the functionality of Payment Orders to support a tier validation process.
Home-page: https://github.com/OCA/bank-payment
Author: Escodoo,Odoo Community Association (OCA)
Author-email: support@odoo-community.org
License: AGPL-3
Classifier: Programming Language :: Python
Classifier: Framework :: Odoo
Classifier: Framework :: Odoo :: 14.0
Classifier: License :: OSI Approved :: GNU Affero General Public License v3
Requires-Python: >=3.6
Requires-Dist: odoo14-addon-account-payment-order
Requires-Dist: odoo14-addon-base-tier-validation
Requires-Dist: odoo<14.1dev,>=14.0a
